auto_file_sorter/__init__.py
auto_file_sorter/__main__.py
auto_file_sorter/args_handling.py
auto_file_sorter/configs_handling.py
auto_file_sorter/constants.py
auto_file_sorter/event_handling.py
auto_file_sorter/main.py
auto_file_sorter/py.typed
auto_file_sorter/utils.py
auto_file_sorter-1.0.4.dist-info/LICENSE
auto_file_sorter-1.0.4.dist-info/METADATA
auto_file_sorter-1.0.4.dist-info/WHEEL
auto_file_sorter-1.0.4.dist-info/entry_points.txt
auto_file_sorter-1.0.4.dist-info/top_level.txt
auto_file_sorter-1.0.4.dist-info/RECORD
