Metadata-Version: 2.1
Name: auto-file-sorter
Version: 1.0.4
Summary: A file sorting automation
Author: realshouzy
Maintainer: realshouzy
License: MIT
Project-URL: Repository, https://github.com/realshouzy/auto-file-sorter
Project-URL: Documentation, https://github.com/realshouzy/auto-file-sorter/blob/main/README.md#documentation
Project-URL: Changelog, https://github.com/realshouzy/auto-file-sorter/commits/
Project-URL: Issues, https://github.com/realshouzy/auto-file-sorter/issues
Keywords: automation,file,sorter,auto,watchdog
Classifier: License :: OSI Approved :: MIT License
Classifier: Programming Language :: Python :: 3
Classifier: Programming Language :: Python :: 3 :: Only
Classifier: Programming Language :: Python :: 3.8
Classifier: Programming Language :: Python :: 3.9
Classifier: Programming Language :: Python :: 3.10
Classifier: Programming Language :: Python :: 3.11
Classifier: Programming Language :: Python :: 3.12
Classifier: Programming Language :: Python :: Implementation :: CPython
Classifier: Programming Language :: Python :: Implementation :: PyPy
Requires-Python: >=3.8
License-File: LICENSE
Requires-Dist: watchdog >=3.0.0
Requires-Dist: typing-extensions >=4.4.0 ; python_version < "3.12"
Provides-Extra: dev
Requires-Dist: bandit ; extra == 'dev'
Requires-Dist: black ; extra == 'dev'
Requires-Dist: covdefaults ; extra == 'dev'
Requires-Dist: coverage ; extra == 'dev'
Requires-Dist: isort ; extra == 'dev'
Requires-Dist: mypy ; extra == 'dev'
Requires-Dist: pre-commit ; extra == 'dev'
Requires-Dist: pylint ; extra == 'dev'
Requires-Dist: pylint-pytest ; extra == 'dev'
Requires-Dist: pytest ; extra == 'dev'
Requires-Dist: ruff ; extra == 'dev'
Requires-Dist: tox ; extra == 'dev'
